LICENSE
http_shrinkwrap/__init__.py
http_shrinkwrap/api.py
http_shrinkwrap/bin.py
http_shrinkwrap-0.1.1.dist-info/entry_points.txt
http_shrinkwrap-0.1.1.dist-info/LICENSE
http_shrinkwrap-0.1.1.dist-info/WHEEL
http_shrinkwrap-0.1.1.dist-info/METADATA
http_shrinkwrap-0.1.1.dist-info/RECORD
