Metadata-Version: 2.1
Name: http-shrinkwrap
Version: 0.1.1
Summary: A command line tool to minimize curl http requests.
Home-page: https://github.com/zrthstr/http_shrinkwrap
License: Apache-2.0
Keywords: curl,pentest,http,cli,poc
Author: zrthstr
Author-email: zrth1k@gmail.com
Requires-Python: >=3.8,<4.0
Classifier: Intended Audience :: Developers
Classifier: Intended Audience :: System Administrators
Classifier: License :: OSI Approved :: Apache Software License
Classifier: Operating System :: POSIX
Classifier: Programming Language :: Python :: 3
Classifier: Programming Language :: Python :: 3.8
Classifier: Programming Language :: Python :: 3.9
Classifier: Topic :: Internet
Classifier: Topic :: Internet :: WWW/HTTP
Classifier: Topic :: Internet :: WWW/HTTP :: Browsers
Classifier: Topic :: Security
Classifier: Topic :: System :: Networking
Classifier: Topic :: Utilities
Requires-Dist: curlify (>=2.2.1,<3.0.0)
Requires-Dist: loguru (>=0.5.3,<0.6.0)
Requires-Dist: psutil (>=5.8.0,<6.0.0)
Requires-Dist: requests (>=2.25.1,<3.0.0)
Requires-Dist: uncurl (>=0.0.11,<0.0.12)
Project-URL: Repository, https://github.com/zrthstr/http_shrinkwrap
